{
  "gitSyncId": "6825c1b226a9710102d64a08_ed3fc456-5c0f-4dc9-9626-0246b527d5e9",
  "unpublishedPage": {
    "layouts": [
      {
        "dsl": {
          "backgroundColor": "none",
          "bottomRow": 480,
          "canExtend": true,
          "containerStyle": "none",
          "detachFromLayout": true,
          "dynamicBindingPathList": [],
          "dynamicTriggerPathList": [],
          "leftColumn": 0,
          "minHeight": 1292,
          "parentColumnSpace": 1,
          "parentRowSpace": 1,
          "rightColumn": 4896,
          "snapColumns": 64,
          "snapRows": 124,
          "topRow": 0,
          "type": "CANVAS_WIDGET",
          "version": 92,
          "widgetId": "0",
          "widgetName": "MainContainer"
        }
      }
    ],
    "name": "Page1",
    "slug": "page1"
  }
}